hippasos
